[
  {
    "name": "VM1",
    "category": {
      "name": "Cat1"
    },
    "drives": [
      {
        "name": "drive3"
      }
    ],
    "organization": {
      "name": "Lavovi",
      "description": "asdgzdg",
      "users": [],
      "virtualMachines": [],
      "drives": [
        {
          "name": "drive3"
        },
        {
          "name": "drive2"
        }
      ]
    }
  },
  {
    "name": "VM2",
    "category": {
      "name": "Cat1"
    },
    "drives": [
      {
        "name": "drive3"
      }
    ],
    "organization": {
      "name": "Lavovi",
      "description": "asdgzdg",
      "users": [],
      "virtualMachines": [],
      "drives": [
        {
          "name": "drive3"
        },
        {
          "name": "drive2"
        }
      ]
    }
  },
  {
    "name": "VM23",
    "category": {
      "name": "Cat1"
    },
    "drives": [
      {
        "name": "drive3"
      }
    ],
    "organization": {
      "name": "Lavovi",
      "description": "asdgzdg",
      "users": [],
      "virtualMachines": [],
      "drives": [
        {
          "name": "drive3"
        },
        {
          "name": "drive2"
        }
      ]
    }
  },
  {
    "name": "VM560",
    "category": {
      "name": "Cat2"
    },
    "drives": [
      {
        "name": "drive3"
      }
    ],
    "organization": {
      "name": "Lavovi",
      "description": "asdgzdg",
      "users": [],
      "virtualMachines": [],
      "drives": [
        {
          "name": "drive3"
        },
        {
          "name": "drive2"
        }
      ]
    }
  },
  {
    "name": "VM123",
    "category": {
      "name": "Cat2"
    },
    "drives": [
      {
        "name": "drive3"
      }
    ],
    "organization": {
      "name": "Lavovi",
      "description": "asdgzdg",
      "users": [],
      "virtualMachines": [],
      "drives": [
        {
          "name": "drive3"
        },
        {
          "name": "drive2"
        }
      ]
    }
  },
  {
    "name": "VM233",
    "category": {
      "name": "Cat2"
    },
    "drives": [
      {
        "name": "drive3"
      }
    ],
    "organization": {
      "name": "Lavovi",
      "description": "asdgzdg",
      "users": [],
      "virtualMachines": [],
      "drives": [
        {
          "name": "drive3"
        },
        {
          "name": "drive2"
        }
      ]
    }
  }
]